mcp_standards/__init__.py
mcp_standards/autolog.py
mcp_standards/enhanced_server.py
mcp_standards/export.py
mcp_standards/model_router.py
mcp_standards/schema_migration.py
mcp_standards/server.py
mcp_standards/hooks/__init__.py
mcp_standards/hooks/capture_hook.py
mcp_standards/hooks/pattern_extractor.py
mcp_standards/hooks/significance_scorer.py
mcp_standards/intelligence/__init__.py
mcp_standards/intelligence/agent_tracker.py
mcp_standards/intelligence/claudemd_manager.py
mcp_standards/intelligence/temporal_graph.py
mcp_standards/intelligence/validation_engine.py
mcp_standards/standards/__init__.py
mcp_standards/standards/config_parser.py
mcp_standards/standards/instruction_generator.py
mcp_standards/standards/standards_extractor.py
mcp_standards-0.1.0a2.dist-info/METADATA
mcp_standards-0.1.0a2.dist-info/WHEEL
mcp_standards-0.1.0a2.dist-info/entry_points.txt
mcp_standards-0.1.0a2.dist-info/licenses/LICENSE
mcp_standards-0.1.0a2.dist-info/RECORD
