Metadata-Version: 2.4
Name: mcp-standards
Version: 0.1.0a2
Summary: Self-learning AI standards system - learns from corrections and auto-updates CLAUDE.md
Project-URL: Homepage, https://github.com/airmcp-com/mcp-standards
Project-URL: Documentation, https://github.com/airmcp-com/mcp-standards#readme
Project-URL: Repository, https://github.com/airmcp-com/mcp-standards
Project-URL: Issues, https://github.com/airmcp-com/mcp-standards/issues
Author-email: Matt Strautmann <matt.strautmann@gmail.com>
License: MIT
License-File: LICENSE
Keywords: ai-assistant,claude,claude-code,knowledge-base,mcp,pattern-learning,self-learning,sqlite
Classifier: Development Status :: 3 - Alpha
Classifier: Intended Audience :: Developers
Classifier: License :: OSI Approved :: MIT License
Classifier: Programming Language :: Python :: 3
Classifier: Programming Language :: Python :: 3.10
Classifier: Programming Language :: Python :: 3.11
Classifier: Programming Language :: Python :: 3.12
Classifier: Programming Language :: Python :: 3.13
Requires-Python: >=3.10
Requires-Dist: mcp>=1.0.0
